[
  {
    "id": "rokka-no-yuusha-episode-1",
    "number": 1,
    "url": "https://anitaku.so//rokka-no-yuusha-episode-1",
    "zId": "rokka-braves-of-the-six-flowers-1995?ep=24390",
    "isFiller": false,
    "title": "The Strongest Man In The World",
    "dId": "rokka-no-yuusha-dub-episode-1"
  },
  {
    "id": "rokka-no-yuusha-episode-2",
    "number": 2,
    "url": "https://anitaku.so//rokka-no-yuusha-episode-2",
    "zId": "rokka-braves-of-the-six-flowers-1995?ep=24391",
    "isFiller": false,
    "title": "First Journey",
    "dId": "rokka-no-yuusha-dub-episode-2"
  },
  {
    "id": "rokka-no-yuusha-episode-3",
    "number": 3,
    "url": "https://anitaku.so//rokka-no-yuusha-episode-3",
    "zId": "rokka-braves-of-the-six-flowers-1995?ep=24392",
    "isFiller": false,
    "title": "The Girl Who Kills Braves",
    "dId": "rokka-no-yuusha-dub-episode-3"
  },
  {
    "id": "rokka-no-yuusha-episode-4",
    "number": 4,
    "url": "https://anitaku.so//rokka-no-yuusha-episode-4",
    "zId": "rokka-braves-of-the-six-flowers-1995?ep=24393",
    "isFiller": false,
    "title": "The Heroes Gather",
    "dId": "rokka-no-yuusha-dub-episode-4"
  },
  {
    "id": "rokka-no-yuusha-episode-5",
    "number": 5,
    "url": "https://anitaku.so//rokka-no-yuusha-episode-5",
    "zId": "rokka-braves-of-the-six-flowers-1995?ep=24394",
    "isFiller": false,
    "title": "The Seventh Brave",
    "dId": "rokka-no-yuusha-dub-episode-5"
  },
  {
    "id": "rokka-no-yuusha-episode-6",
    "number": 6,
    "url": "https://anitaku.so//rokka-no-yuusha-episode-6",
    "zId": "rokka-braves-of-the-six-flowers-1995?ep=24395",
    "isFiller": false,
    "title": "A Trap and a Rout",
    "dId": "rokka-no-yuusha-dub-episode-6"
  },
  {
    "id": "rokka-no-yuusha-episode-7",
    "number": 7,
    "url": "https://anitaku.so//rokka-no-yuusha-episode-7",
    "zId": "rokka-braves-of-the-six-flowers-1995?ep=24396",
    "isFiller": false,
    "title": "The Reasons of the Two",
    "dId": "rokka-no-yuusha-dub-episode-7"
  },
  {
    "id": "rokka-no-yuusha-episode-8",
    "number": 8,
    "url": "https://anitaku.so//rokka-no-yuusha-episode-8",
    "zId": "rokka-braves-of-the-six-flowers-1995?ep=24397",
    "isFiller": false,
    "title": "The Average Man and the Genius",
    "dId": "rokka-no-yuusha-dub-episode-8"
  },
  {
    "id": "rokka-no-yuusha-episode-9",
    "number": 9,
    "url": "https://anitaku.so//rokka-no-yuusha-episode-9",
    "zId": "rokka-braves-of-the-six-flowers-1995?ep=24398",
    "isFiller": false,
    "title": "Blossoms of Doubt",
    "dId": "rokka-no-yuusha-dub-episode-9"
  },
  {
    "id": "rokka-no-yuusha-episode-10",
    "number": 10,
    "url": "https://anitaku.so//rokka-no-yuusha-episode-10",
    "zId": "rokka-braves-of-the-six-flowers-1995?ep=24399",
    "isFiller": false,
    "title": "Desperate Situation",
    "dId": "rokka-no-yuusha-dub-episode-10"
  },
  {
    "id": "rokka-no-yuusha-episode-11",
    "number": 11,
    "url": "https://anitaku.so//rokka-no-yuusha-episode-11",
    "zId": "rokka-braves-of-the-six-flowers-1995?ep=24400",
    "isFiller": false,
    "title": "Counterattack",
    "dId": "rokka-no-yuusha-dub-episode-11"
  },
  {
    "id": "rokka-no-yuusha-episode-12",
    "number": 12,
    "url": "https://anitaku.so//rokka-no-yuusha-episode-12",
    "zId": "rokka-braves-of-the-six-flowers-1995?ep=24401",
    "isFiller": false,
    "title": "The Time to Reveal the Answer",
    "dId": "rokka-no-yuusha-dub-episode-12"
  }
]